pysbr/__init__.py
pysbr/__main__.py
pysbr/utils.py
pysbr/config/__init__.py
pysbr/config/arguments.yaml
pysbr/config/atp.yaml
pysbr/config/baseball.yaml
pysbr/config/basketball.yaml
pysbr/config/brasileiroseriea.yaml
pysbr/config/bundesliga.yaml
pysbr/config/config.py
pysbr/config/dictionary.yaml
pysbr/config/epl.yaml
pysbr/config/eredivisie.yaml
pysbr/config/fields.yaml
pysbr/config/fighting.yaml
pysbr/config/football.yaml
pysbr/config/hockey.yaml
pysbr/config/laliga.yaml
pysbr/config/leagueone.yaml
pysbr/config/ligue1.yaml
pysbr/config/mlb.yaml
pysbr/config/nba.yaml
pysbr/config/ncaab.yaml
pysbr/config/ncaaf.yaml
pysbr/config/nfl.yaml
pysbr/config/nhl.yaml
pysbr/config/primeiraliga.yaml
pysbr/config/search_dictionary.yaml
pysbr/config/seriea.yaml
pysbr/config/soccer.yaml
pysbr/config/sport.py
pysbr/config/sportsbook.py
pysbr/config/sportsbooks.yaml
pysbr/config/tennis.yaml
pysbr/config/ucl.yaml
pysbr/config/uefanationsleague.yaml
pysbr/config/ufc.yaml
pysbr/queries/__init__.py
pysbr/queries/bestlines.py
pysbr/queries/consensusHistory.py
pysbr/queries/currentlines.py
pysbr/queries/eventgroupsbyleague.py
pysbr/queries/eventmarkets.py
pysbr/queries/eventsbydate.py
pysbr/queries/eventsbydaterange.py
pysbr/queries/eventsbyeventgroup.py
pysbr/queries/eventsbyeventids.py
pysbr/queries/eventsbymatchup.py
pysbr/queries/eventsbyparticipants.py
pysbr/queries/eventsbyparticipantsrecent.py
pysbr/queries/leaguehierarchy.py
pysbr/queries/leaguemarkets.py
pysbr/queries/leaguesbyleagueids.py
pysbr/queries/linehistory.py
pysbr/queries/lines.py
pysbr/queries/marketsbymarketids.py
pysbr/queries/openinglines.py
pysbr/queries/query.py
pysbr/queries/searchevents.py
pysbr/queries/searchleagues.py
pysbr/queries/searchsports.py
pysbr/queries/sportsbooks.py
pysbr/queries/team.py
python_sbr-0.3.2.dist-info/LICENSE
python_sbr-0.3.2.dist-info/METADATA
python_sbr-0.3.2.dist-info/WHEEL
python_sbr-0.3.2.dist-info/top_level.txt
python_sbr-0.3.2.dist-info/RECORD
