Metadata-Version: 2.1
Name: python-sbr
Version: 0.3.2
Summary: Access the SportsbookReview GraphQL endpoint.
Home-page: https://github.com/JeMorriso/PySBR
Author: Jeremy Morrison
Author-email: jeremy.morrison36@gmail.com
License: MIT
Keywords: sportsbookreview sportsbook review betting api gambling sports graphql odds
Platform: UNKNOWN
Classifier: License :: OSI Approved :: MIT License
Classifier: Programming Language :: Python :: 3
Classifier: Programming Language :: Python :: 3.9
Requires-Python: >=3.8
Requires-Dist: gql
Requires-Dist: pandas
Requires-Dist: pytz
Requires-Dist: pyyaml
Requires-Dist: fake-useragent
